{"denomination": "HA LAVAGE", "nom_commercial": "SALON LAVOIR GTI", "forme": "SAS", "capital": 38722.05, "naf": "96.01B", "effectif_tranche": "1-2", "cp_siege": "92700", "ville_siege": "COLOMBES", "adresse_siege": "45 RUE FELIX FAURE", "profil": "MONO-laverie \u2705", "finances": [{"annee": 2024, "ca": 100070, "resultat": 16290, "ebe": 26033, "marge_ebitda": 26.0, "marge_nette": 16.3, "croissance_ca": 5.6, "caf": 25380, "fonds_propres": 83466, "dettes_fin": 25752, "salaires": 9676, "salaires_ca": 9.7, "va_ca": 38.7, "tresorerie": 50762, "autonomie": 61.4}, {"annee": 2023, "ca": 94807, "resultat": 13215, "ebe": 25351, "marge_ebitda": 26.7, "marge_nette": 13.9, "salaires_ca": 8.8}, {"annee": 2022, "ca": 79670, "resultat": 31308, "ebe": 3909, "marge_ebitda": 4.9, "marge_nette": 39.3}, {"annee": 2021, "ca": 83288, "resultat": -11551, "ebe": 414, "marge_ebitda": 0.5, "marge_nette": -13.9, "alerte": "d\u00e9ficit COVID"}, {"annee": 2020, "ca": 77776, "resultat": -10787}, {"annee": 2019, "ca": 94977, "resultat": 653, "ebe": 10901, "marge_ebitda": 11.5}], "scoring_financier": {"score": null, "risque": null, "erreur": "Donn\u00e9es financi\u00e8res incompl\u00e8tes"}, "scoring_non_financier": {"score": "16/20", "risque": "faible", "prob_def": 0.51}, "representants": [{"qualite": "Pr\u00e9sident", "nom": "V\u00e9ronique Mott\u00e9", "age": 62, "depuis": "2025-10-30", "cp": "27330", "ville": "Mesnil-en-Ouche", "pm": false}], "observations": "\u2b50 Excellent benchmark libre-service Colombes 92700. Marge EBITDA 26%, salaires/CA 9,7%.", "siren": "341279065"}