{"siren": "789142874", "denomination": "SEKMET", "enseigne": "WASH'N DRY", "forme": "SARL", "capital": null, "naf": "96.01B", "effectif_tranche": "0", "cp_siege": "92300", "ville_siege": "LEVALLOIS-PERRET", "adresse_siege": "3 RUE BAUDIN", "profil": "MONO-laverie \u2705", "finances": [{"annee": 2024, "ca": 44101, "resultat": 347, "ebe": 2541, "marge_ebitda": 5.8, "marge_nette": 0.8, "croissance_ca": -48.6, "caf": 2488, "fonds_propres": -17443, "salaires": 126, "salaires_ca": 0.3, "va_ca": 8.5, "tresorerie": 6685, "autonomie": -22.6}, {"annee": 2023, "ca": 85762, "resultat": 28688, "ebe": 34238, "marge_ebitda": 39.9, "marge_nette": 33.5, "salaires_ca": 0.1}, {"annee": 2021, "ca": 45728, "resultat": 29893, "ebe": 31821, "marge_ebitda": 69.6, "marge_nette": 65.4}, {"annee": 2020, "ca": 18993, "resultat": -5528, "ebe": -4986, "marge_ebitda": -26.3, "marge_nette": -29.1}, {"annee": 2019, "ca": 60826, "resultat": 923}, {"annee": 2018, "ca": 58958, "resultat": -55, "ebe": 2159, "marge_ebitda": 3.7, "marge_nette": -0.1}], "scoring_financier": {"score": null, "erreur": "CA trop faible"}, "scoring_non_financier": {"score": "12/20", "risque": "assez_faible", "prob_def": 1.34}, "representants": [{"qualite": "G\u00e9rant", "nom": "Sylvia Bannais", "age": 59, "depuis": "2016-03-31", "cp": "93200", "ville": "Saint-Denis", "pm": false}], "alerte": "\u26a0\ufe0f Actif net < moiti\u00e9 du capital EN COURS depuis 2015 (chronique)", "observations": "Enseigne WASH'N DRY (r\u00e9seau revendeur identifi\u00e9). Levallois 92300. CA tr\u00e8s volatile, possibles \u00e9critures de holding. Chute CA -49% en 2024."}