{"siren": "819827049", "denomination": "XU", "forme": "SARL", "capital": 500, "naf": "96.01B", "effectif_tranche": "1-2", "cp_siege": "75019", "ville_siege": "PARIS", "adresse_siege": "17 RUE DES FETES", "profil": "MONO-laverie \u2705", "finances": [{"annee": 2024, "ca": 76505, "resultat": -4623, "ebe": -4973, "marge_ebitda": -6.5, "marge_nette": -6.0, "caf": -4623, "fonds_propres": -36808, "salaires": 45649, "salaires_ca": 59.7, "va_ca": 54.4, "tresorerie": 8530, "autonomie": -115.1, "alerte": "d\u00e9ficit"}, {"annee": 2023, "ca": 75881, "resultat": -3086}, {"annee": 2022, "ca": 61332, "resultat": -7494, "ebe": -7397, "marge_ebitda": -12.1, "marge_nette": -12.2, "salaires_ca": 64.2}, {"annee": 2021, "ca": 39777, "resultat": -6633}, {"annee": 2020, "ca": 46661, "resultat": -14666, "ebe": -14340, "marge_ebitda": -30.7, "marge_nette": -31.4, "salaires_ca": 74.4}, {"annee": 2019, "ca": 73567, "resultat": 3383}, {"annee": 2018, "ca": 70135, "resultat": -1677}, {"annee": 2017, "ca": 61166, "resultat": -6808}], "scoring_financier": {"score": null, "erreur": "CA trop faible"}, "scoring_non_financier": {"score": "16/20", "risque": "faible", "prob_def": 0.51}, "representants": [{"qualite": "G\u00e9rant", "nom": "Chunchun Wu", "age": 39, "depuis": "2016-05-20", "cp": "93300", "ville": "Aubervilliers", "pm": false}], "alerte": "\u26a0\ufe0f Actif net < moiti\u00e9 du capital EN COURS depuis 2024", "observations": "Capital tr\u00e8s faible (500\u20ac). D\u00e9ficitaire 5 ann\u00e9es sur 8. Salaires/CA 60% asphyxiant."}